{
    "Ali": [
        {
            "message": "@Connor posted a new update",
            "time": "2025-11-06 17:59:05"
        }
    ],
    "Ben": [],
    "Connor": [
        {
            "message": "@Ali posted a new update",
            "time": "2025-11-06 11:44:17"
        },
        {
            "message": "@Ali posted a new update",
            "time": "2025-11-06 18:15:02"
        },
        {
            "message": "@Ali posted a new update",
            "time": "2025-11-06 18:15:59"
        },
        {
            "message": "@Ali posted a new update",
            "time": "2025-11-06 18:17:52"
        }
    ],
    "Jordan": [
        {
            "message": "@Ali posted a new update",
            "time": "2025-11-06 11:44:17"
        },
        {
            "message": "@Ali posted a new update",
            "time": "2025-11-06 18:15:02"
        },
        {
            "message": "@Ali posted a new update",
            "time": "2025-11-06 18:15:59"
        },
        {
            "message": "@Ali posted a new update",
            "time": "2025-11-06 18:17:52"
        }
    ],
    "Liam": [],
    "Maya": [
        {
            "message": "@Ali posted a new update",
            "time": "2025-11-06 11:44:17"
        },
        {
            "message": "@Connor posted a new update",
            "time": "2025-11-06 17:59:05"
        },
        {
            "message": "@Ali posted a new update",
            "time": "2025-11-06 18:15:02"
        },
        {
            "message": "@Ali posted a new update",
            "time": "2025-11-06 18:15:59"
        },
        {
            "message": "@Ali posted a new update",
            "time": "2025-11-06 18:17:52"
        }
    ],
    "Priya": [],
    "Sofia": [
        {
            "message": "@Connor posted a new update",
            "time": "2025-11-06 17:59:05"
        }
    ]
}